rust_contracts_builder/__init__.py
rust_contracts_builder/__main__.py
rust_contracts_builder/wasm_checker.py
rust_contracts_builder/templates/abigen/Cargo.toml
rust_contracts_builder/templates/abigen/main.rs
rust_contracts_builder/templates/init/.gitignore
rust_contracts_builder/templates/init/_Cargo.toml
rust_contracts_builder/templates/init/build.sh
rust_contracts_builder/templates/init/lib.rs
rust_contracts_builder/templates/init/pytest.ini
rust_contracts_builder/templates/init/test.py
rust_contracts_builder/templates/init/test.sh
rust_contracts_builder-0.2.10.dist-info/LICENSE
rust_contracts_builder-0.2.10.dist-info/METADATA
rust_contracts_builder-0.2.10.dist-info/WHEEL
rust_contracts_builder-0.2.10.dist-info/entry_points.txt
rust_contracts_builder-0.2.10.dist-info/top_level.txt
rust_contracts_builder-0.2.10.dist-info/RECORD
