Metadata-Version: 2.1
Name: rust-contracts-builder
Version: 0.2.10
Summary: Rust Contracts Builder
Home-page: https://github.com/uuosio/rust-contracts-builder
Author: The UUOSIO Team
License: Apache 2.0
Platform: UNKNOWN
License-File: LICENSE
Requires-Dist: toml >=0.10.2
